context_mixer/__init__.py
context_mixer/cli.py
context_mixer/config.py
context_mixer/spec_helpers.py
context_mixer/commands/__init__.py
context_mixer/commands/assemble.py
context_mixer/commands/assemble_spec.py
context_mixer/commands/assembly_strategies.py
context_mixer/commands/assembly_strategies_spec.py
context_mixer/commands/ingest.py
context_mixer/commands/ingest_spec.py
context_mixer/commands/init.py
context_mixer/commands/init_spec.py
context_mixer/commands/open.py
context_mixer/commands/quarantine.py
context_mixer/commands/slice.py
context_mixer/commands/interactions/__init__.py
context_mixer/commands/interactions/resolve_conflicts.py
context_mixer/commands/operations/__init__.py
context_mixer/commands/operations/commit.py
context_mixer/commands/operations/commit_message.py
context_mixer/commands/operations/commit_message_spec.py
context_mixer/commands/operations/commit_spec.py
context_mixer/commands/operations/merge.py
context_mixer/domain/chunking_engine.py
context_mixer/domain/chunking_engine_spec.py
context_mixer/domain/commit_message.py
context_mixer/domain/conflict.py
context_mixer/domain/knowledge.py
context_mixer/domain/knowledge_quarantine.py
context_mixer/domain/knowledge_quarantine_spec.py
context_mixer/domain/knowledge_store.py
context_mixer/domain/knowledge_store_spec.py
context_mixer/domain/llm_instructions.py
context_mixer/domain/prompt_archive.py
context_mixer/domain/vector_knowledge_store.py
context_mixer/examples/knowledge_store_example.py
context_mixer/gateways/__init__.py
context_mixer/gateways/chroma.py
context_mixer/gateways/chroma_spec.py
context_mixer/gateways/git.py
context_mixer/gateways/git_spec.py
context_mixer/gateways/llm.py
context_mixer/gateways/adapters/chroma_adapter.py
context_mixer/gateways/adapters/chroma_adapter_spec.py
context_mixer-0.3.1.dist-info/METADATA
context_mixer-0.3.1.dist-info/WHEEL
context_mixer-0.3.1.dist-info/entry_points.txt
context_mixer-0.3.1.dist-info/top_level.txt
context_mixer-0.3.1.dist-info/RECORD
