Metadata-Version: 2.4
Name: context-mixer
Version: 0.3.1
Summary: A tool to create, organize, merge and deploy reusable context instructions across multiple GenAI coding assistants
Author-email: Stacey Vetzal <stacey@vetzal.com>
License: MIT
Project-URL: Homepage, https://github.com/svetzal/context-mixer
Project-URL: Bug Tracker, https://github.com/svetzal/context-mixer/issues
Classifier: Development Status :: 3 - Alpha
Classifier: Intended Audience :: Developers
Classifier: License :: OSI Approved :: MIT License
Classifier: Programming Language :: Python :: 3
Classifier: Programming Language :: Python :: 3.12
Requires-Python: >=3.12
Requires-Dist: mojentic
Requires-Dist: typer
Requires-Dist: rich
Requires-Dist: pyyaml
Requires-Dist: fastmcp
Requires-Dist: chromadb
Requires-Dist: chroma-hnswlib
Provides-Extra: dev
Requires-Dist: pytest; extra == "dev"
Requires-Dist: pytest-cov; extra == "dev"
Requires-Dist: pytest-mock; extra == "dev"
Requires-Dist: pytest-asyncio; extra == "dev"
Requires-Dist: flake8; extra == "dev"
Requires-Dist: mkdocs; extra == "dev"
Requires-Dist: mkdocs-material; extra == "dev"
Requires-Dist: mkdocs-llmstxt; extra == "dev"
Requires-Dist: mkdocstrings[python]; extra == "dev"
Requires-Dist: griffe-fieldz; extra == "dev"
Requires-Dist: pymdown-extensions; extra == "dev"
